doip_server/__init__.py
doip_server/doip_server.py
doip_server/hierarchical_config_manager.py
doip_server/main.py
doip_server-0.5.4.dist-info/METADATA
doip_server-0.5.4.dist-info/WHEEL
doip_server-0.5.4.dist-info/entry_points.txt
doip_server-0.5.4.dist-info/licenses/LICENSE
doip_server-0.5.4.dist-info/RECORD
