Metadata-Version: 2.4
Name: doip-server
Version: 0.5.4
Summary: DoIP Server and Client implementation with YAML configuration
License: MIT
License-File: LICENSE
Keywords: doip,diagnostics,automotive,uds,iso13400,server,client
Author: Alonso Ramirez
Author-email: alonsoram07@gmail.com
Requires-Python: >=3.10,<3.15
Classifier: Development Status :: 4 - Beta
Classifier: Intended Audience :: Developers
Classifier: License :: OSI Approved :: MIT License
Classifier: Operating System :: OS Independent
Classifier: Programming Language :: Python :: 3
Classifier: Programming Language :: Python :: 3.10
Classifier: Programming Language :: Python :: 3.11
Classifier: Programming Language :: Python :: 3.12
Classifier: Programming Language :: Python :: 3.13
Classifier: Topic :: Software Development :: Libraries :: Python Modules
Classifier: Topic :: System :: Networking
Classifier: Topic :: Communications
Requires-Dist: PyYAML (>=6.0,<7.0)
Requires-Dist: doipclient (>=1.1.7,<2.0.0)
Requires-Dist: psutil (>=7.1.3,<8.0.0)
Project-URL: Bug Tracker, https://github.com/Alonso07/doip_server/issues
Project-URL: Changelog, https://github.com/alonso07/doip_server/blob/main/docs/CHANGELOG.md
Project-URL: Documentation, https://github.com/Alonso07/doip_server/tree/main/docs
Project-URL: Homepage, https://github.com/Alonso07/doip_server
Project-URL: Repository, https://github.com/Alonso07/doip_server
Project-URL: Source Code, https://github.com/alonso07/doip_server
